pyrokinetics_plugin_examples/__init__.py
pyrokinetics_plugin_examples/_version.py
pyrokinetics_plugin_examples/equilibrium.py
pyrokinetics_plugin_examples/gk_input.py
pyrokinetics_plugin_examples/gk_output.py
pyrokinetics_plugin_examples/kinetics.py
pyrokinetics_plugin_examples/utils.py
pyrokinetics_plugin_examples-0.2.1.dist-info/LICENSE
pyrokinetics_plugin_examples-0.2.1.dist-info/METADATA
pyrokinetics_plugin_examples-0.2.1.dist-info/WHEEL
pyrokinetics_plugin_examples-0.2.1.dist-info/entry_points.txt
pyrokinetics_plugin_examples-0.2.1.dist-info/top_level.txt
pyrokinetics_plugin_examples-0.2.1.dist-info/RECORD
