Metadata-Version: 2.1
Name: pyrokinetics-plugin-examples
Version: 0.2.1
Summary: A collection of example plugins for Pyrokinetics
Author-email: Liam Pattinson <liam.pattinson@york.ac.uk>
License: MIT License
Project-URL: Source, https://github.com/LiamPattinson/pyrokinetics-plugin-examples
Project-URL: Tracker, https://github.com/LiamPattinson/pyrokinetics-plugin-examples/issues
Keywords: gyrokinetics,analysis,plasma,research
Classifier: Programming Language :: Python
Classifier: Development Status :: 3 - Alpha
Classifier: Natural Language :: English
Classifier: Intended Audience :: Science/Research
Classifier: License :: OSI Approved :: MIT License
Classifier: Operating System :: OS Independent
Classifier: Programming Language :: Python
Classifier: Topic :: Software Development :: Testing
Classifier: Topic :: Scientific/Engineering :: Physics
Requires-Python: >=3.8
License-File: LICENSE
Requires-Dist: numpy
Provides-Extra: lint
Requires-Dist: black ; extra == 'lint'
Requires-Dist: ruff ; extra == 'lint'
Requires-Dist: isort ; extra == 'lint'
Requires-Dist: docformatter ; extra == 'lint'
Requires-Dist: mypy ; extra == 'lint'
Requires-Dist: refurb ; (python_version >= "3.10") and extra == 'lint'
Provides-Extra: test
Requires-Dist: pytest ; extra == 'test'
Requires-Dist: pytest-sugar ; extra == 'test'
